ckit/__init__.py
ckit/cli.py
ckit/command.py
ckit/config/__init__.py
ckit/config/common.py
ckit/config/config.py
ckit/config/config_files_initiatior.py
ckit/config/config_loader.py
ckit/config/yaml_parser.py
ckit/core.py
ckit/group.py
ckit/screens/group_picker.py
ckit/screens/picker.py
ckit/utils.py
ckit-0.3.0.dist-info/LICENSE
ckit-0.3.0.dist-info/METADATA
ckit-0.3.0.dist-info/WHEEL
ckit-0.3.0.dist-info/entry_points.txt
ckit-0.3.0.dist-info/RECORD
